Workbook

Sheet Improved (140)
A1: item_index | B1: question_id | C1: topic | D1: difficulty | E1: question (first 120 chars) | F1: verdict x1 {q,i} | G1: evidence x1 | H1: verdict x2 {q,i|q,i} | I1: evidence x2 | J1: transition
A2: 1 | B2: q_80947 | C2: Mathematics -> Calculus -> Integral Calculus -> Techniques of Integration -> Single-variable | D2: 4.5 | E2: Evaluate the limit of the Riemann sum as \( n \) approaches infinity for the interval \([0,1]\): \[ \lim _{n\to \infty | F2: yes | G2: converted sum to Riemann integral with linearity split | H2: yes | I2: factored 1/n, split linearly, converted to two integrals | J2: yes->yes
A3: 5 | B3: q_58458 | C3: Mathematics -> Calculus -> Differential Calculus -> Derivatives | D3: 5 | E3: If a function $g(x)$ satisfies $\int_{b}^{b+P}g(x)dx=\int_{c}^{c+P}g(x)dx$ for all $b, c \in \Bbb R$ and a fixed $P$, do | F3: yes | G3: Leibniz rule differentiation yielding g(b+P)=g(c+P) analysis | H3: yes | I3: Leibniz rule differentiation, universal equality implies constant, Yes | J3: yes->yes
A4: 6 | B4: q_62813 | C4: Mathematics -> Calculus -> Integral Calculus -> Techniques of Integration -> Multi-variable | D4: 5.5 | E4: Evaluate the double integral \( \iint\limits_{A} y \, dA \), where the region \( A \) is bounded by the parabola \( x^2 | F4: yes | G4: algebraic intersection via u=x^2, Cartesian Type I setup, inner y-integral | H4: yes | I4: substitution u=x^2 for intersections, Cartesian setup, inner y-integral | J4: yes->yes
A5: 19 | B5: q_98943 | C5: Mathematics -> Geometry -> Plane Geometry -> Area | D5: 4 | E5: The figure shows two concentric circles. If the length of chord AB is 80 units and chord AB is tangent to the smaller ci | F5: yes | G5: perpendicular radius, Pythagorean relation, annulus difference of squares | H5: yes | I5: right triangle at tangency, R^2-r^2=1600, annulus area | J5: yes->yes
A6: 27 | B6: q_65828 | C6: Mathematics -> Algebra -> Abstract Algebra -> Group Theory | D6: 7 | E6: Given a free abelian group $G$ of rank $k$, prove or disprove that if $S$ is a subset of $G$ that is linearly independen | F6: yes | G6: contradiction with k+1 elements plus rank bound, no embedding | H6: yes | I6: embedded in Q vector space, k+1 contradiction via dimension | J6: yes->yes
A7: 40 | B7: q_101640 | C7: Mathematics -> Geometry -> Plane Geometry -> Angles | D7: 5 | E7: Circle $\Gamma$ is the incircle of $\triangle ABC$ and is also the circumcircle of $\triangle XYZ$. The point $X$ is on | F7: yes | G7: equal tangents, isosceles at B, supplementary angle gives 120 | H7: yes | I7: contact triangle, equal tangents isosceles, supplementary angle, 90+B/2 formula | J7: yes->yes
A8: 42 | B8: q_37528 | C8: Mathematics -> Algebra -> Linear Algebra -> Linear Transformations | D8: 8.5 | E8: Let $X$ and $Y$ be Banach spaces. Consider a sequence of invertible operators $T_n \in B(X,Y)$ such that $T_n \xrightarr | F8: yes | G8: passes T_nT_n^{-1}=I to limit via composition continuity | H8: yes | I8: passed T_n T_n^{-1}=I to limit via composition continuity | J8: yes->yes
A9: 62 | B9: q_6255 | C9: Mathematics -> Calculus -> Integral Calculus -> Techniques of Integration -> Single-variable | D9: 8 | E9: Evaluate the contour integral \( \oint_{|z|=1} \sqrt{z} \, dz \) around the unit circle, where \( z = e^{2\pi it} \) for | F9: yes | G9: parameterizes θ∈[0,2π] tracking phase across branch cut | H9: yes | I9: antiderivative jump with phase factor across branch circuit | J9: yes->yes
A10: 64 | B10: q_33198 | C10: Mathematics -> Differential Equations -> Partial Differential Equations (PDEs) | D10: 6 | E10: Consider the heat diffusion problem described by the function: \[ u(x,t)= \frac {a_0}2 + \sum_{n=1}^{\infty} a_n \cos\le | F10: yes | G10: exponential decay terms vanish, steady-state a0/2 remains | H10: yes | I10: decaying exponential modes vanish leaving a0/2 steady state | J10: yes->yes
A11: 69 | B11: q_46507 | C11: Mathematics -> Algebra -> Abstract Algebra -> Ring Theory | D11: 8.5 | E11: Let $A$ be a commutative ring with unit and $M$ a module over $A$. Suppose the rank of $M_{P}$ over $A_{P}$ is constant | F11: yes | G11: fiber-dimension rank definition, torsion-module counterexample construction | H11: yes | I11: recognized tautology, pointwise rank definition, torsion counterexample discussion | J11: yes->yes
A12: 70 | B12: q_35551 | C12: Mathematics -> Calculus -> Differential Calculus -> Applications of Derivatives | D12: 5.5 | E12: Determine the radius of convergence of the power series \( \sum_{n=1}^\infty \frac{(2n)!}{(n!)^2}z^n \). | F12: yes | G12: applies Ratio Test, simplifies factorials, leading-term limit gives 1/4 | H12: yes | I12: ratio test with factorial simplification and leading-term limit | J12: yes->yes
A13: 73 | B13: q_89561 | C13: Mathematics -> Discrete Mathematics -> Combinatorics | D13: 6.5 | E13: In a language with only three letters - $A, B$, and $C$, a word is defined as a sequence of exactly 100 letters, with ex | F13: unclear | G13: mentions 2^40 labelings but hand-waves to unjustified 2^39 | H13: yes | I13: fixed support strategy, distinct labelings giving 2^40 | J13: unclear->yes
... A141: 992 | B141: q_11924 | C141: Mathematics -> Algebra -> Algebra -> Polynomial Operations | D141: 5 | E141: Given that $\alpha, \beta, \gamma, \delta$ are the roots of the polynomial equation $x^4 - 3x + 1 = 0$, find the value o | F141: yes | G141: recursive Newton's Identities for p1,p2,p3 | H141: yes | I141: applies Newton's Identities recursively to get p3 | J141: yes->yes

Sheet Hurt control (117)
A1: item_index | B1: question_id | C1: topic | D1: difficulty | E1: question (first 120 chars) | F1: verdict x1 {q,i} | G1: evidence x1 | H1: verdict x2 {q,i|q,i} | I1: evidence x2 | J1: transition
A2: 2 | B2: q_102284 | C2: Mathematics -> Algebra -> Algebra -> Equations and Inequalities | D2: 5 | E2: Let $x,$ $y,$ $z$ be real numbers such that $x + y + z = 5$ and $xy + xz + yz = 8.$ Find the largest possible value of | F2: yes | G2: discriminant constraint quadratic inequality in x | H2: yes | I2: y,z as quadratic roots, discriminant non-negativity inequality | J2: yes->yes
A3: 4 | B3: q_80009 | C3: Mathematics -> Calculus -> Integral Calculus -> Techniques of Integration -> Single-variable | D3: 8 | E3: Evaluate the integral \( \int_0^e{W(x)}\,\mathrm{d}x \). | F3: yes | G3: inverse-function identity, integration by parts for F | H3: yes | I3: applied inverse-function integral identity with F(f-inverse) | J3: yes->yes
A4: 24 | B4: q_66076 | C4: Mathematics -> Algebra -> Abstract Algebra -> Ring Theory | D4: 8 | E4: Let $R \subseteq S$ be commutative rings such that $R$ is a subring of $S$ with the same unity. Suppose $S$ has an $R$-m | F4: yes | G4: unimodular 1_S, projective module, functional with f(1)=1 | H4: yes | I4: reduced to functional with p(1_S)=1, built splitting projection | J4: yes->yes
A5: 28 | B5: q_101824 | C5: Mathematics -> Algebra -> Prealgebra -> Other | D5: 4 | E5: Convert the base-$64$ number $100_{64}$ to base $62$. | F5: yes | G5: base-10 pivot then greedy power subtraction | H5: yes | I5: Base-10 pivot, exponential shortcut, greedy power subtraction | J5: yes->yes
A6: 53 | B6: q_60790 | C6: Mathematics -> Algebra -> Linear Algebra -> Matrices | D6: 5.5 | E6: Let \( M \) be a \( 3 \times 3 \) matrix such that \( M \begin{bmatrix} -2 \\ 1 \\ 0 \end{bmatrix} = \begin{bmatrix} 6 \ | F6: yes | G6: identified eigenvector, used scalar eigenvalue exponentiation shortcut | H6: yes | I6: Recognized eigenvector, scalar-multiple shortcut, eigenvalue cubed | J6: yes->yes
A7: 58 | B7: q_28464 | C7: Mathematics -> Calculus -> Integral Calculus -> Applications of Integrals | D7: 6.5 | E7: Compute the integral of the curl of the vector field \( F = (x^2+y-4, 3xy, 2xz+z^2) \) over the surface defined by \( x^ | F7: yes | G7: Stokes' theorem, evaluated field at z=0, odd-term vanishing | H7: yes | I7: Stokes' theorem, boundary at z=0, parameterized line integral | J7: yes->yes
A8: 61 | B8: q_10543 | C8: Mathematics -> Algebra -> Abstract Algebra -> Field Theory | D8: 8 | E8: If $a(x)$ and $b(x)$ are rational functions in $x$ with complex coefficients, and $b(x)^2 = a(x)^3 + 1$, does it necessa | F8: yes | G8: genus-1 elliptic curve, no nonconstant maps from P1 | H8: yes | I8: Genus argument with Riemann-Hurwitz contradiction | J8: yes->yes
A9: 77 | B9: q_81392 | C9: Mathematics -> Algebra -> Algebra -> Equations and Inequalities | D9: 5.5 | E9: Let $a, b, x, y$ be real numbers such that $a^2+b^2=81$, $x^2+y^2=121$, and $ax + by = 99$. Determine the set of all pos | F9: yes | G9: Vector interpretation, Cauchy-Schwarz equality, collinearity gives zero | H9: yes | I9: applied Lagrange's identity directly to get zero | J9: yes->yes
A10: 91 | B10: q_68697 | C10: Mathematics -> Algebra -> Abstract Algebra -> Group Theory | D10: 7 | E10: Determine whether a semigroup exists that satisfies the following properties: 1. For all elements $x$ and $y$, there exi | F10: yes | G10: translation surjectivity analysis, tests non-abelian S3 | H10: yes | I10: division property implies group, tested S3 non-commuting pair | J10: yes->yes
A11: 93 | B11: q_92201 | C11: Mathematics -> Number Theory -> Prime Numbers | D11: 5.5 | E11: Let $A$ be a subset of $\{1,2,\ldots,2020\}$ such that the difference of any two distinct elements in $A$ is not prime. | F11: yes | G11: residue class mod 4 construction, multiples of 4 differences | H11: yes | I11: mod 4 residue class construction, block optimality check | J11: yes->yes
A12: 97 | B12: q_100086 | C12: Mathematics -> Geometry -> Plane Geometry -> Angles | D12: 4 | E12: A convex pentagon has interior angles with measures $x+1$, $2x$, $3x$, $4x$, and $5x-1$ degrees. What is the measure of | F12: yes | G12: 540-degree sum, linear equation, convexity check, largest expression | H12: yes | I12: pentagon sum 540, linear equation, evaluated largest expression | J12: yes->yes
A13: 103 | B13: q_84512 | C13: Mathematics -> Calculus -> Integral Calculus -> Applications of Integrals | D13: 5.5 | E13: Calculate the outward flux of the vector field \( F = (x^3, y^3, z^2) \) across the surface of the solid enclosed by the | F13: yes | G13: Divergence Theorem, cylindrical coordinates with Jacobian r | H13: yes | I13: Divergence theorem, cylindrical coordinates with Jacobian | J13: yes->yes
... A118: 998 | B118: q_73165 | C118: Mathematics -> Other | D118: 7.5 | E118: Find the values of $a$ and $b$ such that the series \( \sum_{n=1}^{\infty}(-1)^{n-1}\left(a-\frac{(n-b)^n}{n^n}\right) \ | F118: yes | G118: zeroes limit for a, Taylor expands, applies Leibniz test | H118: yes | I118: term limit zero condition, exponential expansion of remainder | J118: yes->yes

Sheet Summary
A1: Blinded LLM-judge uptake study - Mistral Small 24B, {q,i} vs {q,i|q,i}
A2: All 514 (card, response) pairs judged independently, shuffled, condition and correctness hidden; one fixed rubric identical to the Qwen 7B study (judge: Claude, 2026-07-17). Verdict = does the response APPLY the card's core strategy (solution path, not wording). Improved group: wrong at x1, right at x2. Hurt control: right at x1, wrong at x2.
A4: IMPROVED (wrong -> right): verdict counts
A5: verdict | B5: x1 {q,i} | C5: x2 {q,i|q,i}
A6: yes | B6: =COUNTIF('Improved (140)'!F$2:F$141,$A6) | C6: =COUNTIF('Improved (140)'!H$2:H$141,$A6)
A7: unclear | B7: =COUNTIF('Improved (140)'!F$2:F$141,$A7) | C7: =COUNTIF('Improved (140)'!H$2:H$141,$A7)
A8: no | B8: =COUNTIF('Improved (140)'!F$2:F$141,$A8) | C8: =COUNTIF('Improved (140)'!H$2:H$141,$A8)
A9: yes-rate | B9: =B6/SUM(B6:B8) | C9: =C6/SUM(C6:C8)
A10: uptake gained (non-yes->yes) | B10: =SUMPRODUCT(('Improved (140)'!F$2:F$141<>"yes")*('Improved (140)'!H$2:H$141="yes"))
A11: uptake lost (yes->non-yes) | B11: =SUMPRODUCT(('Improved (140)'!F$2:F$141="yes")*('Improved (140)'!H$2:H$141<>"yes"))
A12: two-sided sign test p | B12: =MIN(1,2*BINOMDIST(MIN(B10,B11),B10+B11,0.5,TRUE))
A14: HURT CONTROL (right -> wrong): verdict counts
A15: verdict | B15: x1 {q,i} | C15: x2 {q,i|q,i}
A16: yes | B16: =COUNTIF('Hurt control (117)'!F$2:F$118,$A16) | C16: =COUNTIF('Hurt control (117)'!H$2:H$118,$A16)
A17: unclear | B17: =COUNTIF('Hurt control (117)'!F$2:F$118,$A17) | C17: =COUNTIF('Hurt control (117)'!H$2:H$118,$A17)
A18: no | B18: =COUNTIF('Hurt control (117)'!F$2:F$118,$A18) | C18: =COUNTIF('Hurt control (117)'!H$2:H$118,$A18)
A19: yes-rate | B19: =B16/SUM(B16:B18) | C19: =C16/SUM(C16:C18)
A20: uptake gained (non-yes->yes) | B20: =SUMPRODUCT(('Hurt control (117)'!F$2:F$118<>"yes")*('Hurt control (117)'!H$2:H$118="yes"))
A21: uptake lost (yes->non-yes) | B21: =SUMPRODUCT(('Hurt control (117)'!F$2:F$118="yes")*('Hurt control (117)'!H$2:H$118<>"yes"))
A22: two-sided sign test p | B22: =MIN(1,2*BINOMDIST(MIN(B20,B21),B20+B21,0.5,TRUE))
A24: Pooled (both groups, 257 items)
A25: yes-rate x1 | B25: =(COUNTIF('Improved (140)'!F2:F141,"yes")+COUNTIF('Hurt control (117)'!F2:F118,"yes"))/257
A26: yes-rate x2 | B26: =(COUNTIF('Improved (140)'!H2:H141,"yes")+COUNTIF('Hurt control (117)'!H2:H118,"yes"))/257
A28: Reading
A29: Replicates the Qwen 7B pattern exactly. Uptake tracks the answer flip in BOTH directions (improved: +10/-0, p=.002; hurt: +0/-8, p=.008) and pooled x1 vs x2 yes-rates are flat (94.9% vs 95.7%). No condition-driven adoption increase is detectable. Mistral applies the card even more consistently than Qwen: 95% of x1 responses in the flip groups already apply it (100% in the hurt group), and not a single yes->non-yes or non-yes->yes transition runs against the correctness coupling. Failures under a single presentation are execution failures, not attention failures; the attention-rescue channel is bounded to <=9% of items for this model.
